app/__init__.py
app/__main__.py
app/funcmodule.py
good_bot_encrypt-1.1.0.dist-info/LICENSE
good_bot_encrypt-1.1.0.dist-info/METADATA
good_bot_encrypt-1.1.0.dist-info/WHEEL
good_bot_encrypt-1.1.0.dist-info/entry_points.txt
good_bot_encrypt-1.1.0.dist-info/top_level.txt
good_bot_encrypt-1.1.0.dist-info/RECORD
