Metadata-Version: 2.1
Name: good-bot-encrypt
Version: 1.1.0
Summary: A simple password manager to be used with Good-Bot.
Home-page: UNKNOWN
Author: Tricky
License: MIT
Platform: UNKNOWN
